nobelium/__init__.py
nobelium/example.py
nobelium-0.0.0.dist-info/LICENCE
nobelium-0.0.0.dist-info/METADATA
nobelium-0.0.0.dist-info/WHEEL
nobelium-0.0.0.dist-info/top_level.txt
nobelium-0.0.0.dist-info/RECORD
