Metadata-Version: 2.1
Name: nobelium
Version: 0.0.0
Summary: A hobby project
Author-email: nobelium <kontakt@matematikk.as>
Project-URL: Homepage, https://matematikk.as
Project-URL: Issues, https://matematikk.as
Classifier: Programming Language :: Python :: 3
Classifier: License :: OSI Approved :: MIT License
Classifier: Operating System :: OS Independent
Requires-Python: >=3.8
License-File: LICENCE
